reqlint/__init__.py
reqlint/reqlint.py
reqlint-0.2.1.dist-info/DESCRIPTION.rst
reqlint-0.2.1.dist-info/entry_points.txt
reqlint-0.2.1.dist-info/METADATA
reqlint-0.2.1.dist-info/metadata.json
reqlint-0.2.1.dist-info/RECORD
reqlint-0.2.1.dist-info/top_level.txt
reqlint-0.2.1.dist-info/WHEEL
